grit_guardian/__init__.py
grit_guardian/analytics/__init__.py
grit_guardian/analytics/analytics.py
grit_guardian/cli/__init__.py
grit_guardian/cli/main.py
grit_guardian/core/__init__.py
grit_guardian/core/habit_tracker.py
grit_guardian/core/models.py
grit_guardian/persistence/__init__.py
grit_guardian/persistence/database_manager.py
grit_guardian/pet/__init__.py
grit_guardian/pet/pet.py
grit_guardian-0.1.1a0.dist-info/LICENSE
grit_guardian-0.1.1a0.dist-info/METADATA
grit_guardian-0.1.1a0.dist-info/WHEEL
grit_guardian-0.1.1a0.dist-info/entry_points.txt
grit_guardian-0.1.1a0.dist-info/RECORD
