Metadata-Version: 2.3
Name: grit-guardian
Version: 0.1.1a0
Summary: Terminal-based habit tracker with virtual companion
License: MIT
Keywords: habit-tracker,cli,productivity,terminal
Author: Patrick Weiss
Author-email: patrick.weiss@iu-study.org
Requires-Python: >=3.11
Classifier: Development Status :: 3 - Alpha
Classifier: Intended Audience :: End Users/Desktop
Classifier: License :: OSI Approved :: MIT License
Classifier: Programming Language :: Python :: 3.11
Requires-Dist: click (>=8.2.1,<9.0.0)
Requires-Dist: sphinx (>=8.2.3,<9.0.0)
Requires-Dist: sphinx-autobuild (>=2024.10.3,<2025.0.0)
Requires-Dist: sphinx-copybutton (>=0.5.2,<0.6.0)
Requires-Dist: sphinxcontrib-mermaid (>=1.0.0,<2.0.0)
Project-URL: Documentation, https://grit-guardian.readthedocs.io
Project-URL: Homepage, https://github.com/pi-weiss/grit-guardian
Project-URL: Repository, https://github.com/pi-weiss/grit-guardian
